{
  "feed_url": "https://smartcanucks.ca/feed/",
  "scraped_at": "2025-08-01T05:38:19.587189Z",
  "scraping_stats": {
    "rss_entries": 20,
    "posts_scraped": 20,
    "merchant_links_found": 0,
    "affiliate_links_processed": 0,
    "affiliate_success_rate": 0
  },
  "blog_posts": [
    {
      "title": "Shoppers Drug Mart Canada: Super Beauty Redemption August 1st – 5th + More",
      "link": "https://smartcanucks.ca/shoppers-drug-mart-canada-super-beauty-redemption-august-1st-5th-more/",
      "published": "2025-08-01T00:35:21Z",
      "affiliate_processed": false,
      "scraped_content": {
        "title": "",
        "content_preview": "",
        "content_summary": "",
        "og_image": null,
        "merchant_links_count": 0,
        "deal_info": {},
        "scraped_at": 1754026651.9237583
      }
    },
    {
      "title": "Sobeys Canada: Get 1,000 Scene+ Points When You Buy 6 Select General Mills Products",
      "link": "https://smartcanucks.ca/sobeys-canada-get-1000-scene-points-when-you-buy-6-select-general-mills-products/",
      "published": "2025-07-31T22:42:27Z",
      "affiliate_processed": false,
      "scraped_content": {
        "title": "",
        "content_preview": "",
        "content_summary": "",
        "og_image": null,
        "merchant_links_count": 0,
        "deal_info": {},
        "scraped_at": 1754026654.5181406
      }
    },
    {
      "title": "Food Basics Ontario: Buy 2 Kellogg’s Family Size Cereal and Get 4 Litres of Milk for Free",
      "link": "https://smartcanucks.ca/food-basics-ontario-buy-2-kelloggs-family-size-cereal-and-get-4-litres-of-milk-for-free/",
      "published": "2025-07-31T21:49:35Z",
      "affiliate_processed": false,
      "scraped_content": {
        "title": "",
        "content_preview": "",
        "content_summary": "",
        "og_image": null,
        "merchant_links_count": 0,
        "deal_info": {},
        "scraped_at": 1754026656.7107828
      }
    },
    {
      "title": "Amazon Canada Deals: Save 64% on URMYWO Busy Board for Toddlers Boys Girls Montessori Toys + More",
      "link": "https://smartcanucks.ca/amazon-canada-deals-save-64-on-urmywo-busy-board-for-toddlers-boys-girls-montessori-toys-more/",
      "published": "2025-07-31T20:45:50Z",
      "affiliate_processed": false,
      "scraped_content": {
        "title": "",
        "content_preview": "",
        "content_summary": "",
        "og_image": null,
        "merchant_links_count": 0,
        "deal_info": {},
        "scraped_at": 1754026659.427599
      }
    },
    {
      "title": "Harry Rosen Canada: End of Season Sale up to 60% off + Extra 20% off",
      "link": "https://smartcanucks.ca/harry-rosen-canada-end-of-season-sale-up-to-60-off-extra-20-off/",
      "published": "2025-07-31T14:10:17Z",
      "affiliate_processed": false,
      "scraped_content": {
        "title": "",
        "content_preview": "",
        "content_summary": "",
        "og_image": null,
        "merchant_links_count": 0,
        "deal_info": {},
        "scraped_at": 1754026662.2764134
      }
    },
    {
      "title": "Amazon Canada Deals: Save 60% on MAXGROOM PRO 7D Electric Head Shaver for Bald Men + More",
      "link": "https://smartcanucks.ca/amazon-canada-deals-save-41-on-maxgroom-pro-7d-electric-head-shaver-for-bald-men-more/",
      "published": "2025-07-31T14:00:17Z",
      "affiliate_processed": false,
      "scraped_content": {
        "title": "",
        "content_preview": "",
        "content_summary": "",
        "og_image": null,
        "merchant_links_count": 0,
        "deal_info": {},
        "scraped_at": 1754026665.1225207
      }
    },
    {
      "title": "H&M Canada: Sale up to 64% off",
      "link": "https://smartcanucks.ca/hm-canada-sale-up-to-64-off/",
      "published": "2025-07-31T13:36:20Z",
      "affiliate_processed": false,
      "scraped_content": {
        "title": "",
        "content_preview": "",
        "content_summary": "",
        "og_image": null,
        "merchant_links_count": 0,
        "deal_info": {},
        "scraped_at": 1754026667.5388627
      }
    },
    {
      "title": "Gap Canada Back To School Event: 40-60% off Select Styles + Extra 50% off Sale",
      "link": "https://smartcanucks.ca/gap-canada-back-to-school-event-40-60-off-select-styles-extra-50-off-sale/",
      "published": "2025-07-31T13:23:56Z",
      "affiliate_processed": false,
      "scraped_content": {
        "title": "",
        "content_preview": "",
        "content_summary": "",
        "og_image": null,
        "merchant_links_count": 0,
        "deal_info": {},
        "scraped_at": 1754026669.9872274
      }
    },
    {
      "title": "Clarins Canada Flash Sale: Save 20% on Moisturizers + Free Gift with Purchase",
      "link": "https://smartcanucks.ca/clarins-canada-flash-sale-save-20-on-moisturizers-free-gift-with-purchase/",
      "published": "2025-07-31T12:36:55Z",
      "affiliate_processed": false,
      "scraped_content": {
        "title": "",
        "content_preview": "",
        "content_summary": "",
        "og_image": null,
        "merchant_links_count": 0,
        "deal_info": {},
        "scraped_at": 1754026672.4498086
      }
    },
    {
      "title": "Eddie Bauer Canada: Clearance up to 70% off + Extra 50% off",
      "link": "https://smartcanucks.ca/eddie-bauer-canada-clearance-up-to-70-off-extra-50-off/",
      "published": "2025-07-31T12:28:04Z",
      "affiliate_processed": false,
      "scraped_content": {
        "title": "",
        "content_preview": "",
        "content_summary": "",
        "og_image": null,
        "merchant_links_count": 0,
        "deal_info": {},
        "scraped_at": 1754026675.3615294
      }
    },
    {
      "title": "Amazon Canada Deals: Save 42% on Mac mini M4 Dock & Stand + 50% on Women’s Ribbed Tank Tops + More",
      "link": "https://smartcanucks.ca/amazon-canada-deals-save-42-on-mac-mini-m4-dock-stand-50-on-womens-ribbed-tank-tops-more/",
      "published": "2025-07-31T03:06:33Z",
      "affiliate_processed": false,
      "scraped_content": {
        "title": "",
        "content_preview": "",
        "content_summary": "",
        "og_image": null,
        "merchant_links_count": 0,
        "deal_info": {},
        "scraped_at": 1754026677.5754635
      }
    },
    {
      "title": "No Frills Ontario Flyer Deals July 31st – August 6th: $1 Wonder Buns + More",
      "link": "https://smartcanucks.ca/no-frills-ontario-flyer-deals-july-31st-august-6th-1-wonder-buns-more/",
      "published": "2025-07-30T23:19:32Z",
      "affiliate_processed": false,
      "scraped_content": {
        "title": "",
        "content_preview": "",
        "content_summary": "",
        "og_image": null,
        "merchant_links_count": 0,
        "deal_info": {},
        "scraped_at": 1754026679.9422596
      }
    },
    {
      "title": "Real Canadian Superstore Ontario Flyer Deals + Bonus Redemption July 31st – August 6th",
      "link": "https://smartcanucks.ca/real-canadian-superstore-ontario-flyer-deals-bonus-redemption-july-31st-august-6th/",
      "published": "2025-07-30T22:33:09Z",
      "affiliate_processed": false,
      "scraped_content": {
        "title": "",
        "content_preview": "",
        "content_summary": "",
        "og_image": null,
        "merchant_links_count": 0,
        "deal_info": {},
        "scraped_at": 1754026682.879248
      }
    },
    {
      "title": "Walmart Canada Flyer Deals July 31st – August 6th: Pint of Blueberries $1.44 + More",
      "link": "https://smartcanucks.ca/walmart-canada-flyer-deals-july-31st-august-6th-pint-of-blueberries-1-44-more/",
      "published": "2025-07-30T22:01:19Z",
      "affiliate_processed": false,
      "scraped_content": {
        "title": "",
        "content_preview": "",
        "content_summary": "",
        "og_image": null,
        "merchant_links_count": 0,
        "deal_info": {},
        "scraped_at": 1754026685.4405975
      }
    },
    {
      "title": "Amazon Canada Deals: Save 64% on URMYWO Busy Board for Toddlers + More",
      "link": "https://smartcanucks.ca/amazon-canada-deals-save-64-on-urmywo-busy-board-for-toddlers-more/",
      "published": "2025-07-30T19:37:46Z",
      "affiliate_processed": false,
      "scraped_content": {
        "title": "",
        "content_preview": "",
        "content_summary": "",
        "og_image": null,
        "merchant_links_count": 0,
        "deal_info": {},
        "scraped_at": 1754026687.6021085
      }
    },
    {
      "title": "Amazon Canada Deals: Save 48% on GKLPO Mini Projector with Built-in Apps Using Promo Code + More Offers",
      "link": "https://smartcanucks.ca/amazon-canada-deals-save-48-on-gklpo-mini-projector-with-built-in-apps-using-promo-code-more-offers/",
      "published": "2025-07-30T18:53:07Z",
      "affiliate_processed": false,
      "scraped_content": {
        "title": "",
        "content_preview": "",
        "content_summary": "",
        "og_image": null,
        "merchant_links_count": 0,
        "deal_info": {},
        "scraped_at": 1754026690.0085921
      }
    },
    {
      "title": "Ardene Canada: Sale up to 50% off + Swim Styles for $8",
      "link": "https://smartcanucks.ca/ardene-canada-sale-up-to-50-off-swim-styles-for-8/",
      "published": "2025-07-30T15:31:30Z",
      "affiliate_processed": false,
      "scraped_content": {
        "title": "",
        "content_preview": "",
        "content_summary": "",
        "og_image": null,
        "merchant_links_count": 0,
        "deal_info": {},
        "scraped_at": 1754026692.4368973
      }
    },
    {
      "title": "Bloomingdale’s Canada: Designer Sale up to 60% off + Clearance up to 75% off",
      "link": "https://smartcanucks.ca/bloomingdales-canada-designer-sale-up-to-60-off-clearance-up-to-75-off/",
      "published": "2025-07-30T15:15:42Z",
      "affiliate_processed": false,
      "scraped_content": {
        "title": "",
        "content_preview": "",
        "content_summary": "",
        "og_image": null,
        "merchant_links_count": 0,
        "deal_info": {},
        "scraped_at": 1754026695.1565158
      }
    },
    {
      "title": "Anna Bella Canada: End or Season Sale up to 70% off + Free Shipping on All Orders",
      "link": "https://smartcanucks.ca/anna-bella-canada-end-or-season-sale-up-to-70-off-free-shipping-on-all-orders/",
      "published": "2025-07-30T14:22:12Z",
      "affiliate_processed": false,
      "scraped_content": {
        "title": "",
        "content_preview": "",
        "content_summary": "",
        "og_image": null,
        "merchant_links_count": 0,
        "deal_info": {},
        "scraped_at": 1754026697.469305
      }
    },
    {
      "title": "American Eagle & Aerie Canada: 30% off All Jeans and Pants + 50-70% off Clearance",
      "link": "https://smartcanucks.ca/american-eagle-aerie-canada-30-off-all-jeans-and-pants-50-70-off-clearance/",
      "published": "2025-07-30T14:03:34Z",
      "affiliate_processed": false,
      "scraped_content": {
        "title": "",
        "content_preview": "",
        "content_summary": "",
        "og_image": null,
        "merchant_links_count": 0,
        "deal_info": {},
        "scraped_at": 1754026699.587094
      }
    }
  ],
  "product_links": [],
  "processing_summary": {
    "total_blog_posts": 20,
    "total_product_links": 0,
    "affiliate_processed": 0,
    "unique_merchants": 0
  }
}